setup.py
distributions_shy_pckg/Binomialdistribution.py
distributions_shy_pckg/Gaussiandistribution.py
distributions_shy_pckg/Generaldistribution.py
distributions_shy_pckg/__init__.py
distributions_shy_pckg.egg-info/PKG-INFO
distributions_shy_pckg.egg-info/SOURCES.txt
distributions_shy_pckg.egg-info/dependency_links.txt
distributions_shy_pckg.egg-info/not-zip-safe
distributions_shy_pckg.egg-info/top_level.txt