Metadata-Version: 1.0
Name: distributions-shy-pckg
Version: 0.1
Summary: Gaussian distributions
Home-page: UNKNOWN
Author: Shyamali Nandanwar
Author-email: UNKNOWN
License: UNKNOWN
Platform: UNKNOWN
